Workbook

Sheet APP
A1: Planejador de Investimentos em Fundos Imobiliários
A2: Simule aportes mensais, renda potencial e uma distribuição educacional por perfil de risco. Edite somente as células azuis.
B4: CONFIGURAÇÕES
B5: Salário mensal | D5: 2000
B6: Rendimento mensal da carteira | D6: 0.006
B7: Sugestão de investimento (30%) | D7: =D5*30% -> 600
B9: INVESTIMENTO MENSAL
B10: Quanto investir por mês? | D10: 200
B11: Por quantos anos? | D11: 5
B12: Taxa de rendimento mensal? | D12: 0.01079
B13: Patrimônio acumulado | D13: =FV(D12,D11*12,-D10) -> 16755.383
B14: Dividendos mensais estimados | D14: =D13*D6 -> 100.5323
B15: Total investido | D15: =D10*D11*12 -> 12000
B16: Ganho estimado | D16: =D13-D15 -> 4755.3828
B18: PRAZO (ANOS) | C18: PATRIMÔNIO | D18: DIVIDENDOS / MÊS
B19: 2 | C19: =FV($D$12,B19*12,-$D$10) -> 5445.5255 | D19: =C19*$D$6 -> 32.673153
B20: 5 | C20: =FV($D$12,B20*12,-$D$10) -> 16755.383 | D20: =C20*$D$6 -> 100.5323
B21: 10 | C21: =FV($D$12,B21*12,-$D$10) -> 48656.843 | D21: =C21*$D$6 -> 291.94106
B22: 20 | C22: =FV($D$12,B22*12,-$D$10) -> 225039.68 | D22: =C22*$D$6 -> 1350.2381
B23: 30 | C23: =FV($D$12,B23*12,-$D$10) -> 864433.93 | D23: =C23*$D$6 -> 5186.6036
B25: ALOCAÇÃO SUGERIDA POR PERFIL
B26: Perfil | C26: Moderado
B27: Valor a investir por mês | C27: =D10 -> 200
B29: TIPO DE FII | C29: PERCENTUAL | D29: VALOR MENSAL
B30: PAPEL | C30: =SUMIFS(Perfis!$D$2:$D$19,Perfis!$B$2:$B$19,$C$26,Perfis!$C$2:$C$19,$B30) -> 0.32 | D30: =C30*$C$27 -> 64
B31: TIJOLO | C31: =SUMIFS(Perfis!$D$2:$D$19,Perfis!$B$2:$B$19,$C$26,Perfis!$C$2:$C$19,$B31) -> 0.35 | D31: =C31*$C$27 -> 70
B32: HÍBRIDOS | C32: =SUMIFS(Perfis!$D$2:$D$19,Perfis!$B$2:$B$19,$C$26,Perfis!$C$2:$C$19,$B32) -> 0.08 | D32: =C32*$C$27 -> 16
B33: FOFs | C33: =SUMIFS(Perfis!$D$2:$D$19,Perfis!$B$2:$B$19,$C$26,Perfis!$C$2:$C$19,$B33) -> 0.05 | D33: =C33*$C$27 -> 10
B34: DESENVOLVIMENTO | C34: =SUMIFS(Perfis!$D$2:$D$19,Perfis!$B$2:$B$19,$C$26,Perfis!$C$2:$C$19,$B34) -> 0.1 | D34: =C34*$C$27 -> 20
B35: HOTELARIAS | C35: =SUMIFS(Perfis!$D$2:$D$19,Perfis!$B$2:$B$19,$C$26,Perfis!$C$2:$C$19,$B35) -> 0.1 | D35: =C35*$C$27 -> 20
B36: TOTAL | D36: =SUM(D30:D35) -> 200
A38: Nota: simulação educacional com taxas constantes. Não representa recomendação nem garantia de rentabilidade; avalie riscos, preços e fundamentos antes de investir.

Sheet Projeção
A1: Mês | B1: Data | C1: Aporte | D1: Saldo inicial | E1: Rendimento | F1: Patrimônio final | G1: Dividendos estimados
A2: 0 | B2: 46294 | C2: 0 | D2: 0 | E2: 0 | F2: 0 | G2: 0
A3: =A2+1 -> 1 | B3: =IF(A3<=APP!$D$11*12,EDATE(B2,1),"") -> 46324 | C3: =IF(A3<=APP!$D$11*12,APP!$D$10,"") -> 200 | D3: =IF(A3<=APP!$D$11*12,F2,"") -> 0 | E3: =IF(A3<=APP!$D$11*12,D3*APP!$D$12,"") -> 0 | F3: =IF(A3<=APP!$D$11*12,D3+E3+C3,"") -> 200 | G3: =IF(A3<=APP!$D$11*12,F3*APP!$D$6,"") -> 1.2
A4: =A3+1 -> 2 | B4: =IF(A4<=APP!$D$11*12,EDATE(B3,1),"") -> 46355 | C4: =IF(A4<=APP!$D$11*12,APP!$D$10,"") -> 200 | D4: =IF(A4<=APP!$D$11*12,F3,"") -> 200 | E4: =IF(A4<=APP!$D$11*12,D4*APP!$D$12,"") -> 2.158 | F4: =IF(A4<=APP!$D$11*12,D4+E4+C4,"") -> 402.158 | G4: =IF(A4<=APP!$D$11*12,F4*APP!$D$6,"") -> 2.412948
A5: =A4+1 -> 3 | B5: =IF(A5<=APP!$D$11*12,EDATE(B4,1),"") -> 46385 | C5: =IF(A5<=APP!$D$11*12,APP!$D$10,"") -> 200 | D5: =IF(A5<=APP!$D$11*12,F4,"") -> 402.158 | E5: =IF(A5<=APP!$D$11*12,D5*APP!$D$12,"") -> 4.3392848 | F5: =IF(A5<=APP!$D$11*12,D5+E5+C5,"") -> 606.49728 | G5: =IF(A5<=APP!$D$11*12,F5*APP!$D$6,"") -> 3.6389837
A6: =A5+1 -> 4 | B6: =IF(A6<=APP!$D$11*12,EDATE(B5,1),"") -> 46416 | C6: =IF(A6<=APP!$D$11*12,APP!$D$10,"") -> 200 | D6: =IF(A6<=APP!$D$11*12,F5,"") -> 606.49728 | E6: =IF(A6<=APP!$D$11*12,D6*APP!$D$12,"") -> 6.5441057 | F6: =IF(A6<=APP!$D$11*12,D6+E6+C6,"") -> 813.04139 | G6: =IF(A6<=APP!$D$11*12,F6*APP!$D$6,"") -> 4.8782483
A7: =A6+1 -> 5 | B7: =IF(A7<=APP!$D$11*12,EDATE(B6,1),"") -> 46446 | C7: =IF(A7<=APP!$D$11*12,APP!$D$10,"") -> 200 | D7: =IF(A7<=APP!$D$11*12,F6,"") -> 813.04139 | E7: =IF(A7<=APP!$D$11*12,D7*APP!$D$12,"") -> 8.7727166 | F7: =IF(A7<=APP!$D$11*12,D7+E7+C7,"") -> 1021.8141 | G7: =IF(A7<=APP!$D$11*12,F7*APP!$D$6,"") -> 6.1308846
A8: =A7+1 -> 6 | B8: =IF(A8<=APP!$D$11*12,EDATE(B7,1),"") -> 46474 | C8: =IF(A8<=APP!$D$11*12,APP!$D$10,"") -> 200 | D8: =IF(A8<=APP!$D$11*12,F7,"") -> 1021.8141 | E8: =IF(A8<=APP!$D$11*12,D8*APP!$D$12,"") -> 11.025374 | F8: =IF(A8<=APP!$D$11*12,D8+E8+C8,"") -> 1232.8395 | G8: =IF(A8<=APP!$D$11*12,F8*APP!$D$6,"") -> 7.3970369
A9: =A8+1 -> 7 | B9: =IF(A9<=APP!$D$11*12,EDATE(B8,1),"") -> 46505 | C9: =IF(A9<=APP!$D$11*12,APP!$D$10,"") -> 200 | D9: =IF(A9<=APP!$D$11*12,F8,"") -> 1232.8395 | E9: =IF(A9<=APP!$D$11*12,D9*APP!$D$12,"") -> 13.302338 | F9: =IF(A9<=APP!$D$11*12,D9+E9+C9,"") -> 1446.1418 | G9: =IF(A9<=APP!$D$11*12,F9*APP!$D$6,"") -> 8.6768509
A10: =A9+1 -> 8 | B10: =IF(A10<=APP!$D$11*12,EDATE(B9,1),"") -> 46535 | C10: =IF(A10<=APP!$D$11*12,APP!$D$10,"") -> 200 | D10: =IF(A10<=APP!$D$11*12,F9,"") -> 1446.1418 | E10: =IF(A10<=APP!$D$11*12,D10*APP!$D$12,"") -> 15.60387 | F10: =IF(A10<=APP!$D$11*12,D10+E10+C10,"") -> 1661.7457 | G10: =IF(A10<=APP!$D$11*12,F10*APP!$D$6,"") -> 9.9704741
A11: =A10+1 -> 9 | B11: =IF(A11<=APP!$D$11*12,EDATE(B10,1),"") -> 46566 | C11: =IF(A11<=APP!$D$11*12,APP!$D$10,"") -> 200 | D11: =IF(A11<=APP!$D$11*12,F10,"") -> 1661.7457 | E11: =IF(A11<=APP!$D$11*12,D11*APP!$D$12,"") -> 17.930236 | F11: =IF(A11<=APP!$D$11*12,D11+E11+C11,"") -> 1879.6759 | G11: =IF(A11<=APP!$D$11*12,F11*APP!$D$6,"") -> 11.278056
A12: =A11+1 -> 10 | B12: =IF(A12<=APP!$D$11*12,EDATE(B11,1),"") -> 46596 | C12: =IF(A12<=APP!$D$11*12,APP!$D$10,"") -> 200 | D12: =IF(A12<=APP!$D$11*12,F11,"") -> 1879.6759 | E12: =IF(A12<=APP!$D$11*12,D12*APP!$D$12,"") -> 20.281703 | F12: =IF(A12<=APP!$D$11*12,D12+E12+C12,"") -> 2099.9576 | G12: =IF(A12<=APP!$D$11*12,F12*APP!$D$6,"") -> 12.599746
A13: =A12+1 -> 11 | B13: =IF(A13<=APP!$D$11*12,EDATE(B12,1),"") -> 46627 | C13: =IF(A13<=APP!$D$11*12,APP!$D$10,"") -> 200 | D13: =IF(A13<=APP!$D$11*12,F12,"") -> 2099.9576 | E13: =IF(A13<=APP!$D$11*12,D13*APP!$D$12,"") -> 22.658543 | F13: =IF(A13<=APP!$D$11*12,D13+E13+C13,"") -> 2322.6162 | G13: =IF(A13<=APP!$D$11*12,F13*APP!$D$6,"") -> 13.935697
A14: =A13+1 -> 12 | B14: =IF(A14<=APP!$D$11*12,EDATE(B13,1),"") -> 46658 | C14: =IF(A14<=APP!$D$11*12,APP!$D$10,"") -> 200 | D14: =IF(A14<=APP!$D$11*12,F13,"") -> 2322.6162 | E14: =IF(A14<=APP!$D$11*12,D14*APP!$D$12,"") -> 25.061028 | F14: =IF(A14<=APP!$D$11*12,D14+E14+C14,"") -> 2547.6772 | G14: =IF(A14<=APP!$D$11*12,F14*APP!$D$6,"") -> 15.286063
... A362: =A361+1 -> 360 | B362: =IF(A362<=APP!$D$11*12,EDATE(B361,1),"") | C362: =IF(A362<=APP!$D$11*12,APP!$D$10,"") | D362: =IF(A362<=APP!$D$11*12,F361,"") | E362: =IF(A362<=APP!$D$11*12,D362*APP!$D$12,"") | F362: =IF(A362<=APP!$D$11*12,D362+E362+C362,"") | G362: =IF(A362<=APP!$D$11*12,F362*APP!$D$6,"")

Sheet Perfis
A1: CHAVE | B1: PERFIL | C1: TIPO DE FII | D1: %
A2: =B2&"-"&C2 -> Conservador-PAPEL | B2: Conservador | C2: PAPEL | D2: 0.3
A3: =B3&"-"&C3 -> Conservador-TIJOLO | B3: Conservador | C3: TIJOLO | D3: 0.5
A4: =B4&"-"&C4 -> Conservador-HÍBRIDOS | B4: Conservador | C4: HÍBRIDOS | D4: 0.1
A5: =B5&"-"&C5 -> Conservador-FOFs | B5: Conservador | C5: FOFs | D5: 0.1
A6: =B6&"-"&C6 -> Conservador-DESENVOLVIMENTO | B6: Conservador | C6: DESENVOLVIMENTO | D6: 0
A7: =B7&"-"&C7 -> Conservador-HOTELARIAS | B7: Conservador | C7: HOTELARIAS | D7: 0
A8: =B8&"-"&C8 -> Moderado-PAPEL | B8: Moderado | C8: PAPEL | D8: 0.32
A9: =B9&"-"&C9 -> Moderado-TIJOLO | B9: Moderado | C9: TIJOLO | D9: 0.35
A10: =B10&"-"&C10 -> Moderado-HÍBRIDOS | B10: Moderado | C10: HÍBRIDOS | D10: 0.08
A11: =B11&"-"&C11 -> Moderado-FOFs | B11: Moderado | C11: FOFs | D11: 0.05
A12: =B12&"-"&C12 -> Moderado-DESENVOLVIMENTO | B12: Moderado | C12: DESENVOLVIMENTO | D12: 0.1
A13: =B13&"-"&C13 -> Moderado-HOTELARIAS | B13: Moderado | C13: HOTELARIAS | D13: 0.1
... A19: =B19&"-"&C19 -> Agressivo-HOTELARIAS | B19: Agressivo | C19: HOTELARIAS | D19: 0.1
